pdf2podcast/__init__.py
pdf2podcast/core/base.py
pdf2podcast/core/llm.py
pdf2podcast/core/managers.py
pdf2podcast/core/parsers.py
pdf2podcast/core/processing.py
pdf2podcast/core/prompt_list.py
pdf2podcast/core/prompts.py
pdf2podcast/core/rag.py
pdf2podcast/core/tts.py
pdf2podcast-0.1.21.dist-info/METADATA
pdf2podcast-0.1.21.dist-info/WHEEL
pdf2podcast-0.1.21.dist-info/top_level.txt
pdf2podcast-0.1.21.dist-info/RECORD
