Metadata-Version: 2.4
Name: pdf2podcast
Version: 0.1.21
Summary: A Python library to convert PDF documents into podcasts
Author-email: Alberto Polini <polini.alberto@gmail.com>
License: MIT
Project-URL: Homepage, https://github.com/albertopolini/pdf2podcast
Requires-Python: >=3.8
Requires-Dist: langchain-anthropic>=0.3.13
Requires-Dist: langchain-google-genai>=0.0.10
Requires-Dist: google-generativeai>=0.3.0
Requires-Dist: python-dotenv>=1.0.1
Requires-Dist: pypdf>=5.5.0
Requires-Dist: langchain-community>=0.0.21
Requires-Dist: pydantic>=2.6.0
Requires-Dist: accelerate>=1.3.0
Requires-Dist: datasets>=3.2.0
Requires-Dist: faiss-cpu>=1.10.0
Requires-Dist: sentence-transformers>=3.4.1
Requires-Dist: pydub>=0.25.1
Requires-Dist: typing-extensions>=4.9.0
Requires-Dist: kokoro>=0.1.0
Requires-Dist: elevenlabs>=2.8.0
Requires-Dist: soundfile>=0.1.0
